Gradient/__init__.py
Gradient/main.py
simpleGradient-1.0.0.dist-info/METADATA
simpleGradient-1.0.0.dist-info/WHEEL
simpleGradient-1.0.0.dist-info/top_level.txt
simpleGradient-1.0.0.dist-info/RECORD
